parsagon/__init__.py
parsagon_server-0.0.3.data/scripts/parsagon-server
parsagon_server-0.0.3.dist-info/LICENSE
parsagon_server-0.0.3.dist-info/METADATA
parsagon_server-0.0.3.dist-info/WHEEL
parsagon_server-0.0.3.dist-info/top_level.txt
parsagon_server-0.0.3.dist-info/RECORD
