Metadata-Version: 2.1
Name: parsagon-server
Version: 0.0.3
Summary: Parsagon Server
Home-page: https://parsagon.io
Author: Sandy Suh
Author-email: sandy@parsagon.io
Classifier: Programming Language :: Python :: 3
Classifier: License :: OSI Approved :: MIT License
Classifier: Operating System :: OS Independent
Requires-Python: >=3.6
License-File: LICENSE
